README.md
setup.py
http_interceptor.egg-info/PKG-INFO
http_interceptor.egg-info/SOURCES.txt
http_interceptor.egg-info/dependency_links.txt
http_interceptor.egg-info/entry_points.txt
http_interceptor.egg-info/requires.txt
http_interceptor.egg-info/top_level.txt
interceptor/__init__.py