Metadata-Version: 1.1
Name: http-interceptor
Version: 0.1.2
Summary: Simple HTTP interceptor
Home-page: UNKNOWN
Author: Joe Paul
Author-email: joeirimpan@gmail.com
License: MIT
Download-URL: https://github.com/joeirimpan/werkzeug-interceptor
Platform: UNKNOWN
Classifier: Development Status :: 4 - Beta
Classifier: Intended Audience :: Developers
Classifier: Programming Language :: Python
Classifier: Natural Language :: English
Classifier: License :: OSI Approved :: MIT License
Classifier: Programming Language :: Python :: 2.6
Classifier: Programming Language :: Python :: 2.7
Classifier: Programming Language :: Python :: 3.3
Classifier: Programming Language :: Python :: 3.4
Classifier: Programming Language :: Python :: 3.5
Classifier: Topic :: Office/Business :: Financial :: Investment
Classifier: Topic :: Software Development :: Libraries :: Python Modules
Classifier: Topic :: Software Development :: Libraries
